mcp_azure_cli/server.py
mcp_azure_cli-0.1.3.dist-info/METADATA
mcp_azure_cli-0.1.3.dist-info/WHEEL
mcp_azure_cli-0.1.3.dist-info/entry_points.txt
mcp_azure_cli-0.1.3.dist-info/licenses/LICENSE
mcp_azure_cli-0.1.3.dist-info/RECORD
